simplejsoner/__init__.py
simplejsoner/core.py
simplejsoner-0.1.3.dist-info/METADATA
simplejsoner-0.1.3.dist-info/WHEEL
simplejsoner-0.1.3.dist-info/RECORD
