Metadata-Version: 2.3
Name: simplejsoner
Version: 0.1.3
Summary: 
Author: qxuwll
Author-email: ivanskarupo23@gmail.com
Requires-Python: >=3.9
Classifier: Programming Language :: Python :: 3
Classifier: Programming Language :: Python :: 3.9
Classifier: Programming Language :: Python :: 3.10
Classifier: Programming Language :: Python :: 3.11
Classifier: Programming Language :: Python :: 3.12
Classifier: Programming Language :: Python :: 3.13
